<?xml version="1.0"?>
<!-- <!DOCTYPE Chapters SYSTEM "matroskachapters.dtd"> -->
<Chapters>
  <EditionEntry>
    <EditionUID>13763247322614151583</EditionUID>
    <EditionFlagDefault>0</EditionFlagDefault>
    <EditionFlagHidden>0</EditionFlagHidden>
    <ChapterAtom>
      <ChapterTimeStart>00:00:00.000000000</ChapterTimeStart>
      <ChapterUID>9835626004215683983</ChapterUID>
      <ChapterFlagHidden>0</ChapterFlagHidden>
      <ChapterFlagEnabled>1</ChapterFlagEnabled>
      <ChapterDisplay>
        <ChapterString>Avant</ChapterString>
        <ChapterLanguage>eng</ChapterLanguage>
      </ChapterDisplay>
    </ChapterAtom>
    <ChapterAtom>
      <ChapterTimeStart>00:00:24.024000000</ChapterTimeStart>
      <ChapterUID>6835761586395344792</ChapterUID>
      <ChapterFlagHidden>0</ChapterFlagHidden>
      <ChapterFlagEnabled>1</ChapterFlagEnabled>
      <ChapterDisplay>
        <ChapterString>OP</ChapterString>
        <ChapterLanguage>eng</ChapterLanguage>
      </ChapterDisplay>
    </ChapterAtom>
    <ChapterAtom>
      <ChapterTimeStart>00:01:54.030577778</ChapterTimeStart>
      <ChapterUID>14319514616518391682</ChapterUID>
      <ChapterFlagHidden>0</ChapterFlagHidden>
      <ChapterFlagEnabled>1</ChapterFlagEnabled>
      <ChapterDisplay>
        <ChapterString>Part A</ChapterString>
        <ChapterLanguage>eng</ChapterLanguage>
      </ChapterDisplay>
    </ChapterAtom>
    <ChapterAtom>
      <ChapterTimeStart>00:11:37.071355556</ChapterTimeStart>
      <ChapterUID>7922121478160297624</ChapterUID>
      <ChapterFlagHidden>0</ChapterFlagHidden>
      <ChapterFlagEnabled>1</ChapterFlagEnabled>
      <ChapterDisplay>
        <ChapterString>Part B</ChapterString>
        <ChapterLanguage>eng</ChapterLanguage>
      </ChapterDisplay>
    </ChapterAtom>
    <ChapterAtom>
      <ChapterTimeStart>00:20:56.004733334</ChapterTimeStart>
      <ChapterUID>13899727930074031800</ChapterUID>
      <ChapterFlagHidden>0</ChapterFlagHidden>
      <ChapterFlagEnabled>1</ChapterFlagEnabled>
      <ChapterDisplay>
        <ChapterString>ED</ChapterString>
        <ChapterLanguage>eng</ChapterLanguage>
      </ChapterDisplay>
    </ChapterAtom>
    <ChapterAtom>
      <ChapterTimeStart>00:22:26.053022222</ChapterTimeStart>
      <ChapterUID>3140495085934754491</ChapterUID>
      <ChapterFlagHidden>0</ChapterFlagHidden>
      <ChapterFlagEnabled>1</ChapterFlagEnabled>
      <ChapterDisplay>
        <ChapterString>Room Camp</ChapterString>
        <ChapterLanguage>eng</ChapterLanguage>
      </ChapterDisplay>
    </ChapterAtom>
    <ChapterAtom>
      <ChapterTimeStart>00:23:25.070333334</ChapterTimeStart>
      <ChapterUID>5224866802811661233</ChapterUID>
      <ChapterDisplay>
        <ChapterString>Next</ChapterString>
        <ChapterLanguage>eng</ChapterLanguage>
      </ChapterDisplay>
      <ChapterFlagHidden>0</ChapterFlagHidden>
      <ChapterFlagEnabled>1</ChapterFlagEnabled>
    </ChapterAtom>
  </EditionEntry>
</Chapters>
